.travis.yml
LICENSE
MANIFEST.in
README.rst
setup.cfg
setup.py
tox.ini
Mopidy_RotaryEncoder.egg-info/PKG-INFO
Mopidy_RotaryEncoder.egg-info/SOURCES.txt
Mopidy_RotaryEncoder.egg-info/dependency_links.txt
Mopidy_RotaryEncoder.egg-info/entry_points.txt
Mopidy_RotaryEncoder.egg-info/not-zip-safe
Mopidy_RotaryEncoder.egg-info/requires.txt
Mopidy_RotaryEncoder.egg-info/top_level.txt
mopidy_rotaryencoder/__init__.py
mopidy_rotaryencoder/ext.conf
mopidy_rotaryencoder/frontend.py
mopidy_rotaryencoder/gpio_input_manager.py
tests/__init__.py
tests/test_extension.py