Metadata-Version: 1.1
Name: Mopidy-RotaryEncoder
Version: 0.1.0
Summary: Mopidy frontend extension to control the volume through a rotary encoder
Home-page: https://github.com/KreMat/mopidy-rotaryencoder
Author: Matthias Kreuzriegler
Author-email: matthias@kreuzriegler.at
License: Apache License, Version 2.0
Platform: UNKNOWN
Classifier: Environment :: No Input/Output (Daemon)
Classifier: Intended Audience :: End Users/Desktop
Classifier: License :: OSI Approved :: Apache Software License
Classifier: Operating System :: OS Independent
Classifier: Programming Language :: Python :: 2
Classifier: Topic :: Multimedia :: Sound/Audio :: Players
